lookout_sdk-0.6.3-py3.6-nspkg.pth
lookout/sdk/__init__.py
lookout/sdk/event_pb2.py
lookout/sdk/event_pb2_grpc.py
lookout/sdk/pb.py
lookout/sdk/service_analyzer.py
lookout/sdk/service_analyzer_pb2.py
lookout/sdk/service_analyzer_pb2_grpc.py
lookout/sdk/service_data.py
lookout/sdk/service_data_pb2.py
lookout/sdk/service_data_pb2_grpc.py
lookout/sdk/grpc/__init__.py
lookout/sdk/grpc/connection.py
lookout/sdk/grpc/log_fields.py
lookout/sdk/grpc/interceptors/__init__.py
lookout/sdk/grpc/interceptors/base.py
lookout/sdk/grpc/interceptors/logger.py
lookout/sdk/test/__init__.py
lookout/sdk/test/mixins.py
tests/__init__.py
tests/spy.py
tests/test_connection.py
tests/test_grpc.py
tests/test_log_fields.py
tests/test_logger_interceptors.py
lookout_sdk-0.6.3.dist-info/METADATA
lookout_sdk-0.6.3.dist-info/WHEEL
lookout_sdk-0.6.3.dist-info/namespace_packages.txt
lookout_sdk-0.6.3.dist-info/top_level.txt
lookout_sdk-0.6.3.dist-info/RECORD
